polarTransform/__init__.py
polarTransform/_version.py
polarTransform/convertToCartesianImage.py
polarTransform/convertToPolarImage.py
polarTransform/imageTransform.py
polarTransform/pointsConversion.py
polarTransform/tests/__init__.py
polarTransform/tests/generateTests.py
polarTransform/tests/test_cartesianConversion.py
polarTransform/tests/test_pointConversion.py
polarTransform/tests/test_polarCartesianConversion.py
polarTransform/tests/test_polarConversion.py
polarTransform/tests/util.py
polarTransform/tests/data/horizontalLines.png
polarTransform/tests/data/horizontalLinesAnimated.avi
polarTransform/tests/data/horizontalLinesAnimatedPolar.avi
polarTransform/tests/data/horizontalLinesPolarImage.png
polarTransform/tests/data/shortAxisApex.png
polarTransform/tests/data/shortAxisApexPolarImage.png
polarTransform/tests/data/shortAxisApexPolarImage_centerMiddle.png
polarTransform/tests/data/verticalLines.png
polarTransform/tests/data/verticalLinesAnimated.avi
polarTransform/tests/data/verticalLinesAnimatedPolar.avi
polarTransform/tests/data/verticalLinesCartesianImageBorders2.png
polarTransform/tests/data/verticalLinesCartesianImageBorders4.png
polarTransform/tests/data/verticalLinesCartesianImage_scaled.png
polarTransform/tests/data/verticalLinesCartesianImage_scaled2.png
polarTransform/tests/data/verticalLinesCartesianImage_scaled3.png
polarTransform/tests/data/verticalLinesPolarImage.png
polarTransform/tests/data/verticalLinesPolarImageBorders.png
polarTransform/tests/data/verticalLinesPolarImageBorders3.png
polarTransform/tests/data/verticalLinesPolarImage_scaled.png
polarTransform/tests/data/verticalLinesPolarImage_scaled2.png
polarTransform/tests/data/verticalLinesPolarImage_scaled3.png
polarTransform-2.0.0.dist-info/LICENSE
polarTransform-2.0.0.dist-info/METADATA
polarTransform-2.0.0.dist-info/WHEEL
polarTransform-2.0.0.dist-info/top_level.txt
polarTransform-2.0.0.dist-info/RECORD
