Metadata-Version: 2.1
Name: polarTransform
Version: 2.0.0
Summary: Library that can converts between polar and cartesian domain with images and individual points.
Home-page: https://github.com/addisonElliott/polarTransform
Author: Addison Elliott
Author-email: addison.elliott@gmail.com
License: MIT License
Project-URL: Documentation, http://polartransform.readthedocs.io
Project-URL: Source, https://github.com/addisonElliott/polarTransform
Project-URL: Tracker, https://github.com/addisonElliott/polarTransform/issues
Keywords: polar transform cartesian conversion logPolar linearPolar cv2 opencv radius theta angle image images
Platform: UNKNOWN
Classifier: Development Status :: 4 - Beta
Classifier: Topic :: Scientific/Engineering
Classifier: License :: OSI Approved :: MIT License
Classifier: Programming Language :: Python :: 3
Classifier: Programming Language :: Python :: 3.4
Classifier: Programming Language :: Python :: 3.5
Classifier: Programming Language :: Python :: 3.6
Requires-Python: >=3
Requires-Dist: numpy
Requires-Dist: scipy
Requires-Dist: scikit-image
